interop_clients/__init__.py
interop_clients/api.py
interop_clients/cli.py
interop_clients/cli_odlc.py
interop_clients/client.py
interop_clients/geo/__init__.py
interop_clients/geo/boundary.py
interop_clients/geo/cli.py
suas_interop_clients-0.1.2.dist-info/entry_points.txt
suas_interop_clients-0.1.2.dist-info/WHEEL
suas_interop_clients-0.1.2.dist-info/METADATA
suas_interop_clients-0.1.2.dist-info/RECORD
