Metadata-Version: 2.1
Name: suas-interop-clients
Version: 0.1.2
Summary: Alternative interop clients for AUVSI SUAS
Author: NC State Aerial Robotics Club
Author-email: aerialroboticsclub@ncsu.edu
Requires-Python: >=3.6,<4.0
Classifier: Programming Language :: Python :: 3
Classifier: Programming Language :: Python :: 3.6
Classifier: Programming Language :: Python :: 3.7
Classifier: Programming Language :: Python :: 3.8
Provides-Extra: geo
Requires-Dist: GDAL (>=3.1.0,<4.0.0); extra == "geo"
Requires-Dist: click (>=6.7,<7.0)
Requires-Dist: pillow (>=7.1.2,<8.0.0)
Requires-Dist: requests (>=2.22.0,<3.0.0)
Requires-Dist: typing-extensions (>=3.7.4,<4.0.0); python_version < "3.8"
